shynais/Shyna_is.py
shynais/Shynais.py
shynais/__init__.py
shynais-0.0.19.dist-info/LICENSE
shynais-0.0.19.dist-info/METADATA
shynais-0.0.19.dist-info/WHEEL
shynais-0.0.19.dist-info/top_level.txt
shynais-0.0.19.dist-info/RECORD
