Metadata-Version: 2.1
Name: shynais
Version: 0.0.19
Summary: Shyna question power package.BASIC META
Author: Shivam Sharma
Author-email: shivamsharma1913@gmail.com
License-File: LICENSE
Requires-Dist: setuptools
Requires-Dist: wheel
Requires-Dist: ShynaDatabase
Requires-Dist: ShynaWeather
Requires-Dist: ShynaGreetings
Requires-Dist: Shynatime
Requires-Dist: haversine
Requires-Dist: wget
